givecolor/__init__.py
givecolor/color.py
givecolor/print_color.py
givecolor-0.1.6.dist-info/LICENSE
givecolor-0.1.6.dist-info/METADATA
givecolor-0.1.6.dist-info/WHEEL
givecolor-0.1.6.dist-info/top_level.txt
givecolor-0.1.6.dist-info/RECORD
