Metadata-Version: 2.1
Name: givecolor
Version: 0.1.6
Summary: Un paquete para imprimir texto de colores en la terminal de Windows
Home-page: https://github.com/JC-Xander/GiveColor
Author: JC-Xander
Author-email: j.xanderoficial@gmail.com
Classifier: Programming Language :: Python :: 3
Classifier: License :: OSI Approved :: MIT License
Classifier: Operating System :: Microsoft :: Windows
Requires-Python: >=3.6
License-File: LICENSE
